bigbluebutton/__init__.py
bigbluebutton/utils.py
bigbluebutton_api-0.8.2.dist-info/LICENSE
bigbluebutton_api-0.8.2.dist-info/METADATA
bigbluebutton_api-0.8.2.dist-info/WHEEL
bigbluebutton_api-0.8.2.dist-info/top_level.txt
bigbluebutton_api-0.8.2.dist-info/RECORD
