Metadata-Version: 2.1
Name: bigbluebutton-api
Version: 0.8.2
Summary: Python API for BigBlueButton.
Home-page: https://github.com/edu2004eu/bigbluebutton-python-api
Author: Reimar Bauer
Author-email: rb.proj@gmail.com
Maintainer: Eduard Luca
Maintainer-email: edu2004eu@gmail.com
License: MIT
Keywords: bigbluebutton
Platform: UNKNOWN
Requires-Dist: requests
